ssb_pdm-0.1.0.dist-info/METADATA
ssb_pdm-0.1.0.dist-info/WHEEL
ssb_pdm/__init__.py
ssb_pdm-0.1.0.dist-info/RECORD
