Metadata-Version: 2.1
Name: ssb-pdm
Version: 0.1.0
Summary: Test pdm
Author-Email: Sergey <sbshab1969@gmail.com>
License: MIT
Requires-Python: >=3.12
Requires-Dist: requests>=2.32.3
